{
  "fileTitle": "data",
  "summaryFileData": {
    "totals": [
      {
        "summaryTotalId": "total-1",
        "total_cust_a": {
          "val": 316
        },
        "total_percent_cust_a": {
          "val": 0.02
        },
        "total_percent_cust_active": {
          "val": 99.98
        },
        "total_cust_s": 2261646,
        "total_outages": 16
      }
    ],
    "date_generated": "2026-05-26T06:22:12.879601186Z",
    "overwritten_ca": false,
    "overwritten_etr": false,
    "page_mode": {
      "mode": "BLUESKY",
      "redirectURL": "",
      "pausePublish": false
    }
  }
}